{
  "id": "t7",
  "who": "worker-1",
  "status": "done",
  "output": "**差別化の切り口**: `resolve_codd_gate`（既存の起動 argv 構築: explicit→PATH→同梱パス）を変更・重複させず、その手前で「未設定時に何を explicit として使うか」を決める姉妹関数 `resolve_codd_gate_bin`（環境変数→設定ファイル値→PATH）として合成可能な形で追加した。\n\n## 成果\n\n`tools/kiro-project/codd_gate_detect.py` に `resolve_codd_gate_bin(config_bin=None, env=None, which=shutil.which) -> str | None` を追加。\n\n- 優先順位: `CODD_GATE_BIN` 環境変数（空白のみは未設定扱い）→ `config_bin`（呼び出し側が設定ファイル読み込み後に渡す値。この関数自身はファイル I/O を行わない — `codd_gate_base.py` の `resolve_base_rev` と同じ最小依存規約）→ `which(BINARY_NAME)` → いずれも無ければ `None`。\n- 例外は一切外へ漏らさない（`which` 呼び出しの想定外例外も含め `try/except Exception: return None` で「未検出」へ縮退）。\n- `env`/`which` を DI 可能にし、既存モジュール群の依存性注入パターンと単体テスト容易性を踏襲。\n- 既存 `resolve_codd_gate` とは責務が異なる（起動 argv 構築 vs. explicit 値の自動決定）ため、`resolve_codd_gate(resolve_codd_gate_bin(cfg.codd_gate_bin), which=shutil.which)` と合成すれば PATH／同梱パス解決までシームレスに繋がる設計にした。\n\n`tools/kiro-project/tests/test_codd_gate_detect.py` に `TestCoddGateResolveBin`（8ケース: env優先／config優先／PATHフォールバック／全滅でNone／空白env・空白configのフォールスルー／実 `os.environ` 経由／`which` 例外の吸収）を追加。\n\n## 検証内容と結果\n\n- `python3 -m pytest tools/kiro-project/tests -q -k codd` → **37 passed**（既存29 + 新規8）\n- 完了条件コマンド一式（pytest -k codd && `codd-gate verify --repos ./.kiro-project/repos.json --repo-dir sandbox=. --base \"${KIRO_BASE_REV:-HEAD~1}\" --strict`）→ **exit 0**（一貫性ゲートも GREEN）\n- `git status`/`git diff --stat` で変更ファイルが `codd_gate_detect.py` と対応テストファイルの2件のみであることを確認（範囲外変更なし）\n\n## 採用した前提・未解決事項・範囲外の所見\n\n- **前提**: 本タスクは検出関数の実装のみが範囲。`CONFIG_DEFAULTS`/`Config`/CLI への `codd_gate_bin` フィールド新設と `regression_cmd`/`intake_cmd`/受入判定への結線は別タスクの責務と判断し、着手していない（t2 の契約表・全体文脈の「結線」は他タスクが担う前提）。\n- **前提**: 「設定ファイル」段は本関数の外でファイルを読み解決済みの値として渡す契約にした（`resolve_base_rev` と同型）。関数自身が yaml を読む実装ではない。\n- **前提**: 戻り値は argv リストではなく実行ファイルパスの文字列（`str | None`）。「実行ファイルの検出」という要求文言に合わせ、`resolve_codd_gate` の argv 構築とは別関心事として分離した。\n- **未解決**: 同梱パス（`tools/codd-gate/codd-gate.py`）フォールバックは要求 3 段（env/config/PATH）に含めなかった。必要なら合成呼び出し `resolve_codd_gate(resolve_codd_gate_bin(...), which=...)` で自動的にカバーされる。\n- **範囲外の所見**: なし（他ファイルは未変更）。",
  "finished_at": "2026-07-13T04:18:12Z",
  "data": {
    "delivery": {
      "url": "https://github.com/ynitto/sandbox/",
      "branch": "kp/kiro-project-codd-gate-171537",
      "commit": "10dcfbf99a34bc93a2eb1b6e770e1fb2200239d8",
      "target": "main",
      "path": ""
    }
  }
}