{
  "id": "t5",
  "who": "worker-2",
  "status": "done",
  "output": "成果物: [git-config-audit.md](/Users/nitto/Workspace/sandbox/.kiro-project/bus/runs/run-20260712-192756-4329/artifacts/t5/git-config-audit.md)\n\n主な実測結果:\n\n- Git: Apple Git 2.50.1\n- 初期ブランチ: `main`\n- `user.name` / `user.email`: 設定あり\n- `core.ignorecase`: `true`\n- `safe.directory`: 未設定\n- 完了条件: `899 passed, 1 skipped`、終了コード 0\n\nソースコード変更、commit、push、ブランチ操作は行っていません。",
  "finished_at": "2026-07-12T10:33:02Z",
  "artifacts": [
    "artifacts/t5/git-config-audit.md"
  ]
}